hikari/__init__.py
hikari/__init__.pyi
hikari/__main__.py
hikari/_about.py
hikari/applications.py
hikari/audit_logs.py
hikari/auto_mod.py
hikari/banner.txt
hikari/channels.py
hikari/cli.py
hikari/colors.py
hikari/colours.py
hikari/commands.py
hikari/components.py
hikari/embeds.py
hikari/emojis.py
hikari/errors.py
hikari/files.py
hikari/guilds.py
hikari/intents.py
hikari/invites.py
hikari/iterators.py
hikari/locales.py
hikari/messages.py
hikari/monetization.py
hikari/permissions.py
hikari/polls.py
hikari/presences.py
hikari/py.typed
hikari/scheduled_events.py
hikari/sessions.py
hikari/snowflakes.py
hikari/stage_instances.py
hikari/stickers.py
hikari/templates.py
hikari/traits.py
hikari/undefined.py
hikari/undefined.pyi
hikari/urls.py
hikari/users.py
hikari/voices.py
hikari/webhooks.py
hikari/api/__init__.py
hikari/api/__init__.pyi
hikari/api/cache.py
hikari/api/config.py
hikari/api/entity_factory.py
hikari/api/event_factory.py
hikari/api/event_manager.py
hikari/api/interaction_server.py
hikari/api/rest.py
hikari/api/shard.py
hikari/api/special_endpoints.py
hikari/api/voice.py
hikari/events/__init__.py
hikari/events/__init__.pyi
hikari/events/application_events.py
hikari/events/auto_mod_events.py
hikari/events/base_events.py
hikari/events/channel_events.py
hikari/events/guild_events.py
hikari/events/interaction_events.py
hikari/events/lifetime_events.py
hikari/events/member_events.py
hikari/events/message_events.py
hikari/events/monetization_events.py
hikari/events/poll_events.py
hikari/events/reaction_events.py
hikari/events/role_events.py
hikari/events/scheduled_events.py
hikari/events/shard_events.py
hikari/events/stage_events.py
hikari/events/typing_events.py
hikari/events/user_events.py
hikari/events/voice_events.py
hikari/impl/__init__.py
hikari/impl/__init__.pyi
hikari/impl/buckets.py
hikari/impl/cache.py
hikari/impl/config.py
hikari/impl/entity_factory.py
hikari/impl/event_factory.py
hikari/impl/event_manager.py
hikari/impl/event_manager_base.py
hikari-2.4.1.dist-info/METADATA
hikari-2.4.1.dist-info/WHEEL
hikari-2.4.1.dist-info/entry_points.txt
hikari-2.4.1.dist-info/licenses/LICENSE
hikari-2.4.1.dist-info/RECORD
