Metadata-Version: 2.4
Name: hikari
Version: 2.4.1
Summary: A sane Discord API for Python 3 built on asyncio and good intentions
Project-URL: Documentation, https://docs.hikari-py.dev/en/stable
Project-URL: Source (GitHub), https://github.com/hikari-py/hikari
Project-URL: Discord, https://discord.gg/Jx4cNGG
Project-URL: Issue Tracker, https://github.com/hikari-py/hikari/issues
Project-URL: CI, https://github.com/hikari-py/hikari/actions
Author: Nekokatt, davfsa
Maintainer-email: davfsa <davfsa@hikari-py.dev>
License: MIT
License-File: LICENSE
Classifier: Development Status :: 5 - Production/Stable
Classifier: Environment :: Console
Classifier: Framework :: AsyncIO
Classifier: Intended Audience :: Developers
Classifier: License :: OSI Approved :: MIT License
Classifier: Natural Language :: English
Classifier: Operating System :: OS Independent
Classifier: Programming Language :: Python :: 3.9
Classifier: Programming Language :: Python :: 3.10
Classifier: Programming Language :: Python :: 3.11
Classifier: Programming Language :: Python :: 3.12
Classifier: Programming Language :: Python :: 3.13
Classifier: Programming Language :: Python :: Implementation :: CPython
Classifier: Topic :: Communications :: Chat
Classifier: Topic :: Internet :: WWW/HTTP
Classifier: Topic :: Software Development :: Libraries
Requires-Python: <3.14,>=3.9.0
Requires-Dist: aiohttp~=3.12
Requires-Dist: attrs~=25.1
Requires-Dist: colorlog~=6.9
Requires-Dist: multidict~=6.1
Provides-Extra: server
Requires-Dist: pynacl~=1.5; extra == 'server'
Provides-Extra: speedups
Requires-Dist: aiohttp[speedups]~=3.11; extra == 'speedups'
Requires-Dist: ciso8601~=2.3; extra == 'speedups'
Requires-Dist: orjson~=3.10; extra == 'speedups'
